{
	"info": {
		"_postman_id": "9ab85bd1-9517-40fa-9135-f4a9fe3fe6f4",
		"name": "Test Explore With Me - Comments",
		"description": "Тесты для проверки работоспособности дополнитеьной функциональности по добавлениюб комментариев к событиям.",
		"schema": "https://schema.getpostman.com/json/collection/v2.1.0/collection.json",
		"_exporter_id": "31230138"
	},
	"item": [
		{
			"name": "Создание нового комментария",
			"event": [
				{
					"listen": "prerequest",
					"script": {
						"exec": [
							"const main = async () => {\r",
							"    const api = new API(pm);\r",
							"    const rnd = new RandomUtils();\r",
							"\r",
							"    try {\r",
							"        const user = await api.addUser(rnd.getUser());\r",
							"        const category = await api.addCategory(rnd.getCategory());\r",
							"        let eventBody = rnd.getEvent(category.id);\r",
							"        eventBody['requestModeration'] = true\r",
							"        let event = await api.addEvent(user.id, eventBody);\r",
							"        event = await api.publishEvent(event.id);\r",
							"\r",
							"        pm.collectionVariables.set(\"uid\", user.id);\r",
							"        pm.collectionVariables.set(\"eid\", event.id);\r",
							"\r",
							"    } catch(err) {\r",
							"        console.error(\"Ошибка при подготовке тестовых данных.\", err);\r",
							"    }\r",
							"};\r",
							"\r",
							"const interval = setInterval(() => {}, 1000);\r",
							"\r",
							"setTimeout(async () => \r",
							"    {\r",
							"        try {\r",
							"            // выполняем наш скрипт\r",
							"            await main();\r",
							"        } catch (e) {\r",
							"            console.error(e);\r",
							"        } finally {\r",
							"            clearInterval(interval);\r",
							"        }\r",
							"    },  \r",
							"    100 \r",
							");"
						],
						"type": "text/javascript",
						"packages": {}
					}
				},
				{
					"listen": "test",
					"script": {
						"exec": [
							"pm.test(\"Ответ должен содержать код статуса 201 и данные в формате json\", function () {\r",
							"    pm.response.to.be.success;    \r",
							"    pm.response.to.be.withBody;\r",
							"    pm.response.to.be.json;\r",
							"});\r",
							"\r",
							"const source = JSON.parse(pm.request.body.raw);\r",
							"const target = pm.response.json();\r",
							"\r",
							"pm.test(\"Комментарий должен содержать поля: id, text, authorName, eventId, create\", function () {\r",
							"pm.expect(target).to.have.property('id');\r",
							"pm.expect(target).to.have.property('text');\r",
							"pm.expect(target).to.have.property('authorName');\r",
							"pm.expect(target).to.have.property('eventId');\r",
							"pm.expect(target).to.have.property('create');\r",
							"});\r",
							"\r",
							"pm.test(\"Данные в ответе должны соответствовать данным в запросе\", function () {\r",
							"    pm.expect(target.text).equal(source.text, 'Содержание комментария должно соответствовать тексту в запросе');\r",
							"});"
						],
						"type": "text/javascript",
						"packages": {}
					}
				}
			],
			"request": {
				"method": "POST",
				"header": [],
				"body": {
					"mode": "raw",
					"raw": "{\r\n    \"text\": \"Новый комментарий для события\"\r\n}",
					"options": {
						"raw": {
							"language": "json"
						}
					}
				},
				"url": {
					"raw": "{{baseUrl}}/users/:userId/events/:eventId/comments",
					"host": [
						"{{baseUrl}}"
					],
					"path": [
						"users",
						":userId",
						"events",
						":eventId",
						"comments"
					],
					"variable": [
						{
							"key": "userId",
							"value": "{{uid}}",
							"description": "id текущего пользователя"
						},
						{
							"key": "eventId",
							"value": "{{eid}}",
							"description": "id текущего события"
						}
					]
				}
			},
			"response": []
		},
		{
			"name": "Создание комментария к несуществующему событию",
			"event": [
				{
					"listen": "prerequest",
					"script": {
						"exec": [
							"const main = async () => {\r",
							"    const api = new API(pm);\r",
							"    const rnd = new RandomUtils();\r",
							"\r",
							"    try {\r",
							"        const user = await api.addUser(rnd.getUser());\r",
							"        const category = await api.addCategory(rnd.getCategory());\r",
							"        let eventBody = rnd.getEvent(category.id);\r",
							"        eventBody['requestModeration'] = true\r",
							"        let event = await api.addEvent(user.id, eventBody);\r",
							"        event = await api.publishEvent(event.id);\r",
							"\r",
							"        pm.collectionVariables.set(\"uid\", user.id);\r",
							"        pm.collectionVariables.set(\"eid\", event.id);\r",
							"\r",
							"    } catch(err) {\r",
							"        console.error(\"Ошибка при подготовке тестовых данных.\", err);\r",
							"    }\r",
							"};\r",
							"\r",
							"const interval = setInterval(() => {}, 1000);\r",
							"\r",
							"setTimeout(async () => \r",
							"    {\r",
							"        try {\r",
							"            // выполняем наш скрипт\r",
							"            await main();\r",
							"        } catch (e) {\r",
							"            console.error(e);\r",
							"        } finally {\r",
							"            clearInterval(interval);\r",
							"        }\r",
							"    },  \r",
							"    100 \r",
							");"
						],
						"type": "text/javascript",
						"packages": {}
					}
				},
				{
					"listen": "test",
					"script": {
						"exec": [
							"pm.test(\"Статус ответа 404. Событие не найдено.\", function () {\r",
							"    pm.expect(pm.response.code).to.be.oneOf([404]);\r",
							"});"
						],
						"type": "text/javascript",
						"packages": {}
					}
				}
			],
			"request": {
				"method": "POST",
				"header": [],
				"body": {
					"mode": "raw",
					"raw": "{\r\n    \"text\": \"Новый комментарий для события\"\r\n}",
					"options": {
						"raw": {
							"language": "json"
						}
					}
				},
				"url": {
					"raw": "{{baseUrl}}/users/:userId/events/:eventId/comments",
					"host": [
						"{{baseUrl}}"
					],
					"path": [
						"users",
						":userId",
						"events",
						":eventId",
						"comments"
					],
					"variable": [
						{
							"key": "userId",
							"value": "{{uid}}",
							"description": "id текущего пользователя"
						},
						{
							"key": "eventId",
							"value": "9999",
							"description": "id события "
						}
					]
				}
			},
			"response": []
		},
		{
			"name": "Создание комментария к неопубликованному событию",
			"event": [
				{
					"listen": "prerequest",
					"script": {
						"exec": [
							"const main = async () => {\r",
							"    const api = new API(pm);\r",
							"    const rnd = new RandomUtils();\r",
							"\r",
							"    try {\r",
							"        const user = await api.addUser(rnd.getUser());\r",
							"        const category = await api.addCategory(rnd.getCategory());\r",
							"        let eventBody = rnd.getEvent(category.id);\r",
							"        eventBody['requestModeration'] = true\r",
							"        let event = await api.addEvent(user.id, eventBody);\r",
							"\r",
							"        pm.collectionVariables.set(\"uid\", user.id);\r",
							"        pm.collectionVariables.set(\"eid\", event.id);\r",
							"\r",
							"    } catch(err) {\r",
							"        console.error(\"Ошибка при подготовке тестовых данных.\", err);\r",
							"    }\r",
							"};\r",
							"\r",
							"const interval = setInterval(() => {}, 1000);\r",
							"\r",
							"setTimeout(async () => \r",
							"    {\r",
							"        try {\r",
							"            // выполняем наш скрипт\r",
							"            await main();\r",
							"        } catch (e) {\r",
							"            console.error(e);\r",
							"        } finally {\r",
							"            clearInterval(interval);\r",
							"        }\r",
							"    },  \r",
							"    100 \r",
							");"
						],
						"type": "text/javascript",
						"packages": {}
					}
				},
				{
					"listen": "test",
					"script": {
						"exec": [
							"pm.test(\"Статус ответа 409. Событие не опубликовано.\", function () {\r",
							"    pm.expect(pm.response.code).to.be.oneOf([409]);\r",
							"});"
						],
						"type": "text/javascript",
						"packages": {}
					}
				}
			],
			"request": {
				"method": "POST",
				"header": [],
				"body": {
					"mode": "raw",
					"raw": "{\r\n    \"text\": \"Новый комментарий для события\"\r\n}",
					"options": {
						"raw": {
							"language": "json"
						}
					}
				},
				"url": {
					"raw": "{{baseUrl}}/users/:userId/events/:eventId/comments",
					"host": [
						"{{baseUrl}}"
					],
					"path": [
						"users",
						":userId",
						"events",
						":eventId",
						"comments"
					],
					"variable": [
						{
							"key": "userId",
							"value": "{{uid}}",
							"description": "id текущего пользователя"
						},
						{
							"key": "eventId",
							"value": "{{eid}}",
							"description": "id события "
						}
					]
				}
			},
			"response": []
		},
		{
			"name": "Создание комментария без содержания",
			"event": [
				{
					"listen": "prerequest",
					"script": {
						"exec": [
							"const main = async () => {\r",
							"    const api = new API(pm);\r",
							"    const rnd = new RandomUtils();\r",
							"\r",
							"    try {\r",
							"        const user = await api.addUser(rnd.getUser());\r",
							"        const category = await api.addCategory(rnd.getCategory());\r",
							"        let eventBody = rnd.getEvent(category.id);\r",
							"        eventBody['requestModeration'] = true\r",
							"        let event = await api.addEvent(user.id, eventBody);\r",
							"        event = await api.publishEvent(event.id);\r",
							"\r",
							"        pm.collectionVariables.set(\"uid\", user.id);\r",
							"        pm.collectionVariables.set(\"eid\", event.id);\r",
							"\r",
							"    } catch(err) {\r",
							"        console.error(\"Ошибка при подготовке тестовых данных.\", err);\r",
							"    }\r",
							"};\r",
							"\r",
							"const interval = setInterval(() => {}, 1000);\r",
							"\r",
							"setTimeout(async () => \r",
							"    {\r",
							"        try {\r",
							"            // выполняем наш скрипт\r",
							"            await main();\r",
							"        } catch (e) {\r",
							"            console.error(e);\r",
							"        } finally {\r",
							"            clearInterval(interval);\r",
							"        }\r",
							"    },  \r",
							"    100 \r",
							");"
						],
						"type": "text/javascript",
						"packages": {}
					}
				},
				{
					"listen": "test",
					"script": {
						"exec": [
							"pm.test(\"Статус ответа 400. Комментарий без содержания.\", function () {\r",
							"    pm.expect(pm.response.code).to.be.oneOf([400]);\r",
							"});"
						],
						"type": "text/javascript",
						"packages": {}
					}
				}
			],
			"request": {
				"method": "POST",
				"header": [],
				"body": {
					"mode": "raw",
					"raw": "",
					"options": {
						"raw": {
							"language": "json"
						}
					}
				},
				"url": {
					"raw": "{{baseUrl}}/users/:userId/events/:eventId/comments",
					"host": [
						"{{baseUrl}}"
					],
					"path": [
						"users",
						":userId",
						"events",
						":eventId",
						"comments"
					],
					"variable": [
						{
							"key": "userId",
							"value": "{{uid}}",
							"description": "id текущего пользователя"
						},
						{
							"key": "eventId",
							"value": "{{eid}}",
							"description": "id события "
						}
					]
				}
			},
			"response": []
		},
		{
			"name": "Получение комментария по id",
			"event": [
				{
					"listen": "prerequest",
					"script": {
						"exec": [
							"const main = async () => {\r",
							"    const api = new API(pm);\r",
							"    const rnd = new RandomUtils();\r",
							"\r",
							"    try {\r",
							"        const user = await api.addUser(rnd.getUser());\r",
							"        const category = await api.addCategory(rnd.getCategory());\r",
							"        let eventBody = rnd.getEvent(category.id);\r",
							"        eventBody['requestModeration'] = true\r",
							"        let event = await api.addEvent(user.id, eventBody);\r",
							"        event = await api.publishEvent(event.id);\r",
							"        const comment = await api.addComment(user.id, event.id, rnd.getComment());\r",
							"\r",
							"        pm.collectionVariables.set(\"uid\", user.id);\r",
							"        pm.collectionVariables.set(\"commentId\", comment.id);\r",
							"         pm.collectionVariables.set(\"response\", comment);\r",
							"        \r",
							"    } catch(err) {\r",
							"        console.error(\"Ошибка при подготовке тестовых данных.\", err);\r",
							"    }\r",
							"};\r",
							"\r",
							"const interval = setInterval(() => {}, 1000);\r",
							"\r",
							"setTimeout(async () => \r",
							"    {\r",
							"        try {\r",
							"            // выполняем наш скрипт\r",
							"            await main();\r",
							"        } catch (e) {\r",
							"            console.error(e);\r",
							"        } finally {\r",
							"            clearInterval(interval);\r",
							"        }\r",
							"    },  \r",
							"    100 \r",
							");"
						],
						"type": "text/javascript",
						"packages": {}
					}
				},
				{
					"listen": "test",
					"script": {
						"exec": [
							"pm.test(\"Ответ должен содержать код статуса 200 и данные в формате json\", function () {\r",
							"    pm.response.to.be.ok;    \r",
							"    pm.response.to.be.withBody;\r",
							"    pm.response.to.be.json;\r",
							"});\r",
							"\r",
							"const source = pm.collectionVariables.get('response');\r",
							"const target = pm.response.json();\r",
							"\r",
							"pm.test(\"Комментарий должен содержать поля: id, text, authorName, eventId, create\", function () {\r",
							"pm.expect(target).to.have.property('id');\r",
							"pm.expect(target).to.have.property('text');\r",
							"pm.expect(target).to.have.property('authorName');\r",
							"pm.expect(target).to.have.property('eventId');\r",
							"pm.expect(target).to.have.property('create');\r",
							"});"
						],
						"type": "text/javascript",
						"packages": {}
					}
				}
			],
			"request": {
				"method": "GET",
				"header": [],
				"url": {
					"raw": "{{baseUrl}}/users/:userId/comments/:commentId",
					"host": [
						"{{baseUrl}}"
					],
					"path": [
						"users",
						":userId",
						"comments",
						":commentId"
					],
					"variable": [
						{
							"key": "userId",
							"value": "{{uid}}",
							"description": "id пользователя"
						},
						{
							"key": "commentId",
							"value": "{{commentId}}",
							"description": "id комментария"
						}
					]
				}
			},
			"response": []
		},
		{
			"name": "Получение комментария по несуществующему id",
			"event": [
				{
					"listen": "prerequest",
					"script": {
						"exec": [
							"const main = async () => {\r",
							"    const api = new API(pm);\r",
							"    const rnd = new RandomUtils();\r",
							"\r",
							"    try {\r",
							"        const user = await api.addUser(rnd.getUser());\r",
							"        const category = await api.addCategory(rnd.getCategory());\r",
							"        let eventBody = rnd.getEvent(category.id);\r",
							"        eventBody['requestModeration'] = true\r",
							"        let event = await api.addEvent(user.id, eventBody);\r",
							"        event = await api.publishEvent(event.id);\r",
							"        const comment = await api.addComment(user.id, event.id, rnd.getComment());\r",
							"\r",
							"        pm.collectionVariables.set(\"uid\", user.id);\r",
							"        pm.collectionVariables.set(\"eid\", event.id);\r",
							"        pm.collectionVariables.set(\"commentId\", comment.id);\r",
							"    } catch(err) {\r",
							"        console.error(\"Ошибка при подготовке тестовых данных.\", err);\r",
							"    }\r",
							"};\r",
							"\r",
							"const interval = setInterval(() => {}, 1000);\r",
							"\r",
							"setTimeout(async () => \r",
							"    {\r",
							"        try {\r",
							"            // выполняем наш скрипт\r",
							"            await main();\r",
							"        } catch (e) {\r",
							"            console.error(e);\r",
							"        } finally {\r",
							"            clearInterval(interval);\r",
							"        }\r",
							"    },  \r",
							"    100 \r",
							");"
						],
						"type": "text/javascript",
						"packages": {}
					}
				},
				{
					"listen": "test",
					"script": {
						"exec": [
							"pm.test(\"Статус ответа 404. Комменатрий не сущесвтует.\", function () {\r",
							"    pm.expect(pm.response.code).to.be.oneOf([404]);\r",
							"});"
						],
						"type": "text/javascript",
						"packages": {}
					}
				}
			],
			"request": {
				"method": "GET",
				"header": [],
				"url": {
					"raw": "{{baseUrl}}/users/:userId/comments/:commentId",
					"host": [
						"{{baseUrl}}"
					],
					"path": [
						"users",
						":userId",
						"comments",
						":commentId"
					],
					"variable": [
						{
							"key": "userId",
							"value": "{{uid}}",
							"description": "id пользователя"
						},
						{
							"key": "commentId",
							"value": "9999",
							"description": "id комменатрия "
						}
					]
				}
			},
			"response": []
		},
		{
			"name": "Получение всех комментариев к событию",
			"event": [
				{
					"listen": "prerequest",
					"script": {
						"exec": [
							"const main = async () => {\r",
							"    const api = new API(pm);\r",
							"    const rnd = new RandomUtils();\r",
							"\r",
							"    try {\r",
							"        const user1 = await api.addUser(rnd.getUser());\r",
							"        const user2 = await api.addUser(rnd.getUser());\r",
							"\r",
							"        const category = await api.addCategory(rnd.getCategory());\r",
							"        let eventBody = rnd.getEvent(category.id);\r",
							"        eventBody['requestModeration'] = true\r",
							"        let event = await api.addEvent(user1.id, eventBody);\r",
							"        event = await api.publishEvent(event.id);\r",
							"        const comment1 = await api.addComment(user1.id, event.id, rnd.getComment());\r",
							"        const comment2 = await api.addComment(user2.id, event.id, rnd.getComment());\r",
							"\r",
							"        pm.collectionVariables.set(\"uid\", user1.id);\r",
							"        pm.collectionVariables.set(\"eid\", event.id);\r",
							"        pm.collectionVariables.set(\"response\", [{comment1}, {comment2}]);\r",
							"\r",
							"    } catch(err) {\r",
							"        console.error(\"Ошибка при подготовке тестовых данных.\", err);\r",
							"    }\r",
							"};\r",
							"\r",
							"const interval = setInterval(() => {}, 1000);\r",
							"\r",
							"setTimeout(async () => \r",
							"    {\r",
							"        try {\r",
							"            // выполняем наш скрипт\r",
							"            await main();\r",
							"        } catch (e) {\r",
							"            console.error(e);\r",
							"        } finally {\r",
							"            clearInterval(interval);\r",
							"        }\r",
							"    },  \r",
							"    100 \r",
							");"
						],
						"type": "text/javascript",
						"packages": {}
					}
				},
				{
					"listen": "test",
					"script": {
						"exec": [
							"pm.test(\"Ответ должен содержать код статуса 200\", function () {\r",
							"    pm.response.to.be.ok;\r",
							"});\r",
							"pm.test(\"Ответ должен содержать список комментариев\", function () {\r",
							"    pm.response.to.be.withBody;\r",
							"    pm.response.to.be.json;\r",
							"    var jsonData = pm.response.json();\r",
							"    pm.expect(jsonData.length, 'длина списка должна быть равна 2').to.eql(2);\r",
							"});"
						],
						"type": "text/javascript",
						"packages": {}
					}
				}
			],
			"request": {
				"method": "GET",
				"header": [],
				"url": {
					"raw": "{{baseUrl}}/user/events/:eventId/comments",
					"host": [
						"{{baseUrl}}"
					],
					"path": [
						"user",
						"events",
						":eventId",
						"comments"
					],
					"variable": [
						{
							"key": "eventId",
							"value": "{{eid}}",
							"description": "id текущего события "
						}
					]
				}
			},
			"response": []
		},
		{
			"name": "Получение всех комментариев к несуществующему событию",
			"event": [
				{
					"listen": "prerequest",
					"script": {
						"exec": [
							"const main = async () => {\r",
							"    const api = new API(pm);\r",
							"    const rnd = new RandomUtils();\r",
							"\r",
							"    try {\r",
							"        const user1 = await api.addUser(rnd.getUser());\r",
							"        const user2 = await api.addUser(rnd.getUser());\r",
							"\r",
							"        const category = await api.addCategory(rnd.getCategory());\r",
							"        let eventBody = rnd.getEvent(category.id);\r",
							"        eventBody['requestModeration'] = true\r",
							"        let event = await api.addEvent(user1.id, eventBody);\r",
							"        event = await api.publishEvent(event.id);\r",
							"        const comment1 = await api.addComment(user1.id, event.id, rnd.getComment());\r",
							"        const comment2 = await api.addComment(user2.id, event.id, rnd.getComment());\r",
							"\r",
							"        pm.collectionVariables.set(\"uid\", user1.id);\r",
							"        pm.collectionVariables.set(\"eid\", event.id);\r",
							"        pm.collectionVariables.set(\"response\", [{comment1}, {comment2}]);\r",
							"\r",
							"    } catch(err) {\r",
							"        console.error(\"Ошибка при подготовке тестовых данных.\", err);\r",
							"    }\r",
							"};\r",
							"\r",
							"const interval = setInterval(() => {}, 1000);\r",
							"\r",
							"setTimeout(async () => \r",
							"    {\r",
							"        try {\r",
							"            // выполняем наш скрипт\r",
							"            await main();\r",
							"        } catch (e) {\r",
							"            console.error(e);\r",
							"        } finally {\r",
							"            clearInterval(interval);\r",
							"        }\r",
							"    },  \r",
							"    100 \r",
							");"
						],
						"type": "text/javascript",
						"packages": {}
					}
				},
				{
					"listen": "test",
					"script": {
						"exec": [
							"pm.test(\"Статус ответа 404. Событие не найдено.\", function () {\r",
							"    pm.expect(pm.response.code).to.be.oneOf([404]);\r",
							"});"
						],
						"type": "text/javascript",
						"packages": {}
					}
				}
			],
			"request": {
				"method": "GET",
				"header": [],
				"url": {
					"raw": "{{baseUrl}}/user/events/:eventId/comments",
					"host": [
						"{{baseUrl}}"
					],
					"path": [
						"user",
						"events",
						":eventId",
						"comments"
					],
					"variable": [
						{
							"key": "eventId",
							"value": "9999",
							"description": "id текущего события "
						}
					]
				}
			},
			"response": []
		},
		{
			"name": "Обновление комментария автором",
			"event": [
				{
					"listen": "prerequest",
					"script": {
						"exec": [
							"const main = async () => {\r",
							"    const api = new API(pm);\r",
							"    const rnd = new RandomUtils();\r",
							"\r",
							"    try {\r",
							"        const user = await api.addUser(rnd.getUser());\r",
							"        const category = await api.addCategory(rnd.getCategory());\r",
							"        let eventBody = rnd.getEvent(category.id);\r",
							"        eventBody['requestModeration'] = true\r",
							"        let event = await api.addEvent(user.id, eventBody);\r",
							"        event = await api.publishEvent(event.id);\r",
							"        const comment = await api.addComment(user.id, event.id, rnd.getComment());\r",
							"\r",
							"        pm.collectionVariables.set(\"uid\", user.id);\r",
							"        pm.collectionVariables.set(\"commentId\", comment.id);\r",
							"        \r",
							"    } catch(err) {\r",
							"        console.error(\"Ошибка при подготовке тестовых данных.\", err);\r",
							"    }\r",
							"};\r",
							"\r",
							"const interval = setInterval(() => {}, 1000);\r",
							"\r",
							"setTimeout(async () => \r",
							"    {\r",
							"        try {\r",
							"            // выполняем наш скрипт\r",
							"            await main();\r",
							"        } catch (e) {\r",
							"            console.error(e);\r",
							"        } finally {\r",
							"            clearInterval(interval);\r",
							"        }\r",
							"    },  \r",
							"    100 \r",
							");"
						],
						"type": "text/javascript",
						"packages": {}
					}
				},
				{
					"listen": "test",
					"script": {
						"exec": [
							"pm.test(\"Ответ должен содержать код статуса 200 и данные в формате json\", function () {\r",
							"    pm.response.to.be.ok;    \r",
							"    pm.response.to.be.withBody;\r",
							"    pm.response.to.be.json;\r",
							"});\r",
							"\r",
							"const source = JSON.parse(pm.request.body.raw);\r",
							"const target = pm.response.json();\r",
							"\r",
							"pm.test(\"Комментарий должен содержать поля: id, text, authorName, eventId, create\", function () {\r",
							"pm.expect(target).to.have.property('id');\r",
							"pm.expect(target).to.have.property('text');\r",
							"pm.expect(target).to.have.property('authorName');\r",
							"pm.expect(target).to.have.property('eventId');\r",
							"pm.expect(target).to.have.property('create');\r",
							"});\r",
							"\r",
							"pm.test(\"Данные комментария должны быть обвнолены\", function () {\r",
							"pm.expect(target.text).equal(source.text, 'Содержание комментария должно соответствовать тексту в запросе');\r",
							"});"
						],
						"type": "text/javascript",
						"packages": {}
					}
				}
			],
			"request": {
				"method": "PATCH",
				"header": [],
				"body": {
					"mode": "raw",
					"raw": "{\r\n    \"text\": \"Обновленный комментарий\"\r\n}",
					"options": {
						"raw": {
							"language": "json"
						}
					}
				},
				"url": {
					"raw": "{{baseUrl}}/users/:userId/comments/:commentId",
					"host": [
						"{{baseUrl}}"
					],
					"path": [
						"users",
						":userId",
						"comments",
						":commentId"
					],
					"variable": [
						{
							"key": "userId",
							"value": "{{uid}}",
							"description": "id  пользователя "
						},
						{
							"key": "commentId",
							"value": "{{commentId}}",
							"description": "id комментария "
						}
					]
				}
			},
			"response": []
		},
		{
			"name": "Обновление комментария с пустым содержанием",
			"event": [
				{
					"listen": "prerequest",
					"script": {
						"exec": [
							"const main = async () => {\r",
							"    const api = new API(pm);\r",
							"    const rnd = new RandomUtils();\r",
							"\r",
							"    try {\r",
							"        const user = await api.addUser(rnd.getUser());\r",
							"        const category = await api.addCategory(rnd.getCategory());\r",
							"        let eventBody = rnd.getEvent(category.id);\r",
							"        eventBody['requestModeration'] = true\r",
							"        let event = await api.addEvent(user.id, eventBody);\r",
							"        event = await api.publishEvent(event.id);\r",
							"        const comment = await api.addComment(user.id, event.id, rnd.getComment());\r",
							"\r",
							"        pm.collectionVariables.set(\"uid\", user.id);\r",
							"        pm.collectionVariables.set(\"commentId\", comment.id);\r",
							"         pm.collectionVariables.set(\"response\", comment);\r",
							"        \r",
							"    } catch(err) {\r",
							"        console.error(\"Ошибка при подготовке тестовых данных.\", err);\r",
							"    }\r",
							"};\r",
							"\r",
							"const interval = setInterval(() => {}, 1000);\r",
							"\r",
							"setTimeout(async () => \r",
							"    {\r",
							"        try {\r",
							"            // выполняем наш скрипт\r",
							"            await main();\r",
							"        } catch (e) {\r",
							"            console.error(e);\r",
							"        } finally {\r",
							"            clearInterval(interval);\r",
							"        }\r",
							"    },  \r",
							"    100 \r",
							");"
						],
						"type": "text/javascript",
						"packages": {}
					}
				},
				{
					"listen": "test",
					"script": {
						"exec": [
							"pm.test(\"Статус ответа 400. Обновление комменатрий не имеет содержания.\", function () {\r",
							"    pm.expect(pm.response.code).to.be.oneOf([400]);\r",
							"});"
						],
						"type": "text/javascript",
						"packages": {}
					}
				}
			],
			"request": {
				"method": "PATCH",
				"header": [],
				"url": {
					"raw": "{{baseUrl}}/users/:userId/comments/:commentId",
					"host": [
						"{{baseUrl}}"
					],
					"path": [
						"users",
						":userId",
						"comments",
						":commentId"
					],
					"variable": [
						{
							"key": "userId",
							"value": "{{uid}}",
							"description": "id пользователя"
						},
						{
							"key": "commentId",
							"value": "{{commentId}}",
							"description": "id комментария"
						}
					]
				}
			},
			"response": []
		},
		{
			"name": "Обновление комментария пользователем не являющимся автором",
			"event": [
				{
					"listen": "prerequest",
					"script": {
						"exec": [
							"const main = async () => {\r",
							"    const api = new API(pm);\r",
							"    const rnd = new RandomUtils();\r",
							"\r",
							"    try {\r",
							"        const user1 = await api.addUser(rnd.getUser());\r",
							"        const user2 = await api.addUser(rnd.getUser());\r",
							"        const category = await api.addCategory(rnd.getCategory());\r",
							"        let eventBody = rnd.getEvent(category.id);\r",
							"        eventBody['requestModeration'] = true\r",
							"        let event = await api.addEvent(user1.id, eventBody);\r",
							"        event = await api.publishEvent(event.id);\r",
							"        const comment = await api.addComment(user2.id, event.id, rnd.getComment());\r",
							"\r",
							"        pm.collectionVariables.set(\"uid\", user1.id);\r",
							"        pm.collectionVariables.set(\"commentId\", comment.id);\r",
							"        pm.collectionVariables.set(\"response\", comment);\r",
							"        \r",
							"    } catch(err) {\r",
							"        console.error(\"Ошибка при подготовке тестовых данных.\", err);\r",
							"    }\r",
							"};\r",
							"\r",
							"const interval = setInterval(() => {}, 1000);\r",
							"\r",
							"setTimeout(async () => \r",
							"    {\r",
							"        try {\r",
							"            // выполняем наш скрипт\r",
							"            await main();\r",
							"        } catch (e) {\r",
							"            console.error(e);\r",
							"        } finally {\r",
							"            clearInterval(interval);\r",
							"        }\r",
							"    },  \r",
							"    100 \r",
							");"
						],
						"type": "text/javascript",
						"packages": {}
					}
				},
				{
					"listen": "test",
					"script": {
						"exec": [
							"pm.test(\"Статус ответа 409. Пользователь не является автором.\", function () {\r",
							"    pm.expect(pm.response.code).to.be.oneOf([409]);\r",
							"});"
						],
						"type": "text/javascript",
						"packages": {}
					}
				}
			],
			"request": {
				"method": "PATCH",
				"header": [],
				"body": {
					"mode": "raw",
					"raw": "{\r\n    \"text\": \"Обновленный комментарий\"\r\n}",
					"options": {
						"raw": {
							"language": "json"
						}
					}
				},
				"url": {
					"raw": "{{baseUrl}}/users/:userId/comments/:commentId",
					"host": [
						"{{baseUrl}}"
					],
					"path": [
						"users",
						":userId",
						"comments",
						":commentId"
					],
					"variable": [
						{
							"key": "userId",
							"value": "{{uid}}",
							"description": "id пользователя"
						},
						{
							"key": "commentId",
							"value": "{{commentId}}",
							"description": "id комментария"
						}
					]
				}
			},
			"response": []
		},
		{
			"name": "Удаление комментария автором",
			"event": [
				{
					"listen": "prerequest",
					"script": {
						"exec": [
							"const main = async () => {\r",
							"    const api = new API(pm);\r",
							"    const rnd = new RandomUtils();\r",
							"\r",
							"    try {\r",
							"        const user = await api.addUser(rnd.getUser());\r",
							"        const category = await api.addCategory(rnd.getCategory());\r",
							"        let eventBody = rnd.getEvent(category.id);\r",
							"        eventBody['requestModeration'] = true\r",
							"        let event = await api.addEvent(user.id, eventBody);\r",
							"        event = await api.publishEvent(event.id);\r",
							"        const comment = await api.addComment(user.id, event.id, rnd.getComment());\r",
							"\r",
							"        pm.collectionVariables.set(\"uid\", user.id);\r",
							"        pm.collectionVariables.set(\"commentId\", comment.id);\r",
							"        \r",
							"    } catch(err) {\r",
							"        console.error(\"Ошибка при подготовке тестовых данных.\", err);\r",
							"    }\r",
							"};\r",
							"\r",
							"const interval = setInterval(() => {}, 1000);\r",
							"\r",
							"setTimeout(async () => \r",
							"    {\r",
							"        try {\r",
							"            // выполняем наш скрипт\r",
							"            await main();\r",
							"        } catch (e) {\r",
							"            console.error(e);\r",
							"        } finally {\r",
							"            clearInterval(interval);\r",
							"        }\r",
							"    },  \r",
							"    100 \r",
							");"
						],
						"type": "text/javascript",
						"packages": {}
					}
				},
				{
					"listen": "test",
					"script": {
						"exec": [
							"pm.test(\"Ответ должен содержать код статуса 204\", function () {\r",
							"    pm.response.to.have.status(204);\r",
							"});"
						],
						"type": "text/javascript",
						"packages": {}
					}
				}
			],
			"request": {
				"method": "DELETE",
				"header": [],
				"url": {
					"raw": "{{baseUrl}}/users/:userId/comments/:commentId",
					"host": [
						"{{baseUrl}}"
					],
					"path": [
						"users",
						":userId",
						"comments",
						":commentId"
					],
					"variable": [
						{
							"key": "userId",
							"value": "{{uid}}",
							"description": "id  пользователя "
						},
						{
							"key": "commentId",
							"value": "{{commentId}}",
							"description": "id комментария "
						}
					]
				}
			},
			"response": []
		},
		{
			"name": "Удаление комментария пользователем не являющимся автором",
			"event": [
				{
					"listen": "prerequest",
					"script": {
						"exec": [
							"const main = async () => {\r",
							"    const api = new API(pm);\r",
							"    const rnd = new RandomUtils();\r",
							"\r",
							"    try {\r",
							"        const user1 = await api.addUser(rnd.getUser());\r",
							"        const user2 = await api.addUser(rnd.getUser());\r",
							"        const category = await api.addCategory(rnd.getCategory());\r",
							"        let eventBody = rnd.getEvent(category.id);\r",
							"        eventBody['requestModeration'] = true\r",
							"        let event = await api.addEvent(user1.id, eventBody);\r",
							"        event = await api.publishEvent(event.id);\r",
							"        const comment = await api.addComment(user2.id, event.id, rnd.getComment());\r",
							"\r",
							"        pm.collectionVariables.set(\"uid\", user1.id);\r",
							"        pm.collectionVariables.set(\"commentId\", comment.id);\r",
							"        pm.collectionVariables.set(\"response\", comment);\r",
							"        \r",
							"    } catch(err) {\r",
							"        console.error(\"Ошибка при подготовке тестовых данных.\", err);\r",
							"    }\r",
							"};\r",
							"\r",
							"const interval = setInterval(() => {}, 1000);\r",
							"\r",
							"setTimeout(async () => \r",
							"    {\r",
							"        try {\r",
							"            // выполняем наш скрипт\r",
							"            await main();\r",
							"        } catch (e) {\r",
							"            console.error(e);\r",
							"        } finally {\r",
							"            clearInterval(interval);\r",
							"        }\r",
							"    },  \r",
							"    100 \r",
							");"
						],
						"type": "text/javascript",
						"packages": {}
					}
				},
				{
					"listen": "test",
					"script": {
						"exec": [
							"pm.test(\"Статус ответа 409. Пользователь не является автором.\", function () {\r",
							"    pm.expect(pm.response.code).to.be.oneOf([409]);\r",
							"});"
						],
						"type": "text/javascript",
						"packages": {}
					}
				}
			],
			"request": {
				"method": "DELETE",
				"header": [],
				"url": {
					"raw": "{{baseUrl}}/users/:userId/comments/:commentId",
					"host": [
						"{{baseUrl}}"
					],
					"path": [
						"users",
						":userId",
						"comments",
						":commentId"
					],
					"variable": [
						{
							"key": "userId",
							"value": "{{uid}}",
							"description": "id пользователя"
						},
						{
							"key": "commentId",
							"value": "{{commentId}}",
							"description": "id комментария"
						}
					]
				}
			},
			"response": []
		},
		{
			"name": "Изменение комментария администратором",
			"event": [
				{
					"listen": "prerequest",
					"script": {
						"exec": [
							"const main = async () => {\r",
							"    const api = new API(pm);\r",
							"    const rnd = new RandomUtils();\r",
							"\r",
							"    try {\r",
							"        const user = await api.addUser(rnd.getUser());\r",
							"        const category = await api.addCategory(rnd.getCategory());\r",
							"        let eventBody = rnd.getEvent(category.id);\r",
							"        eventBody['requestModeration'] = true\r",
							"        let event = await api.addEvent(user.id, eventBody);\r",
							"        event = await api.publishEvent(event.id);\r",
							"        const comment = await api.addComment(user.id, event.id, rnd.getComment());\r",
							"\r",
							"        pm.collectionVariables.set(\"uid\", user.id);\r",
							"        pm.collectionVariables.set(\"commentId\", comment.id);\r",
							"        \r",
							"    } catch(err) {\r",
							"        console.error(\"Ошибка при подготовке тестовых данных.\", err);\r",
							"    }\r",
							"};\r",
							"\r",
							"const interval = setInterval(() => {}, 1000);\r",
							"\r",
							"setTimeout(async () => \r",
							"    {\r",
							"        try {\r",
							"            // выполняем наш скрипт\r",
							"            await main();\r",
							"        } catch (e) {\r",
							"            console.error(e);\r",
							"        } finally {\r",
							"            clearInterval(interval);\r",
							"        }\r",
							"    },  \r",
							"    100 \r",
							");"
						],
						"type": "text/javascript",
						"packages": {}
					}
				},
				{
					"listen": "test",
					"script": {
						"exec": [
							"pm.test(\"Ответ должен содержать код статуса 200 и данные в формате json\", function () {\r",
							"    pm.response.to.be.ok;    \r",
							"    pm.response.to.be.withBody;\r",
							"    pm.response.to.be.json;\r",
							"});\r",
							"\r",
							"const source = JSON.parse(pm.request.body.raw);\r",
							"const target = pm.response.json();\r",
							"\r",
							"pm.test(\"Комментарий должен содержать поля: id, text, authorName, eventId, create\", function () {\r",
							"pm.expect(target).to.have.property('id');\r",
							"pm.expect(target).to.have.property('text');\r",
							"pm.expect(target).to.have.property('authorName');\r",
							"pm.expect(target).to.have.property('eventId');\r",
							"pm.expect(target).to.have.property('create');\r",
							"});\r",
							"\r",
							"pm.test(\"Данные комментария должны быть обвнолены\", function () {\r",
							"pm.expect(target.text).equal(source.text, 'Содержание комментария должно соответствовать тексту в запросе');\r",
							"});"
						],
						"type": "text/javascript",
						"packages": {}
					}
				}
			],
			"request": {
				"method": "PATCH",
				"header": [],
				"body": {
					"mode": "raw",
					"raw": "{\r\n    \"text\": \"Обновленный комментарий\"\r\n}",
					"options": {
						"raw": {
							"language": "json"
						}
					}
				},
				"url": {
					"raw": "{{baseUrl}}/admin/comments/:commentId",
					"host": [
						"{{baseUrl}}"
					],
					"path": [
						"admin",
						"comments",
						":commentId"
					],
					"variable": [
						{
							"key": "commentId",
							"value": "{{commentId}}",
							"description": "id комментария "
						}
					]
				}
			},
			"response": []
		},
		{
			"name": "Изменение комментария администратором с пустым содержанием",
			"event": [
				{
					"listen": "prerequest",
					"script": {
						"exec": [
							"const main = async () => {\r",
							"    const api = new API(pm);\r",
							"    const rnd = new RandomUtils();\r",
							"\r",
							"    try {\r",
							"        const user = await api.addUser(rnd.getUser());\r",
							"        const category = await api.addCategory(rnd.getCategory());\r",
							"        let eventBody = rnd.getEvent(category.id);\r",
							"        eventBody['requestModeration'] = true\r",
							"        let event = await api.addEvent(user.id, eventBody);\r",
							"        event = await api.publishEvent(event.id);\r",
							"        const comment = await api.addComment(user.id, event.id, rnd.getComment());\r",
							"\r",
							"        pm.collectionVariables.set(\"uid\", user.id);\r",
							"        pm.collectionVariables.set(\"commentId\", comment.id);\r",
							"         pm.collectionVariables.set(\"response\", comment);\r",
							"        \r",
							"    } catch(err) {\r",
							"        console.error(\"Ошибка при подготовке тестовых данных.\", err);\r",
							"    }\r",
							"};\r",
							"\r",
							"const interval = setInterval(() => {}, 1000);\r",
							"\r",
							"setTimeout(async () => \r",
							"    {\r",
							"        try {\r",
							"            // выполняем наш скрипт\r",
							"            await main();\r",
							"        } catch (e) {\r",
							"            console.error(e);\r",
							"        } finally {\r",
							"            clearInterval(interval);\r",
							"        }\r",
							"    },  \r",
							"    100 \r",
							");"
						],
						"type": "text/javascript",
						"packages": {}
					}
				},
				{
					"listen": "test",
					"script": {
						"exec": [
							"pm.test(\"Статус ответа 400. Обновление комменатрий не имеет содержания.\", function () {\r",
							"    pm.expect(pm.response.code).to.be.oneOf([400]);\r",
							"});"
						],
						"type": "text/javascript",
						"packages": {}
					}
				}
			],
			"request": {
				"method": "PATCH",
				"header": [],
				"body": {
					"mode": "raw",
					"raw": "",
					"options": {
						"raw": {
							"language": "json"
						}
					}
				},
				"url": {
					"raw": "{{baseUrl}}/admin/comments/:commentId",
					"host": [
						"{{baseUrl}}"
					],
					"path": [
						"admin",
						"comments",
						":commentId"
					],
					"variable": [
						{
							"key": "commentId",
							"value": "{{commentId}}",
							"description": "id комментария"
						}
					]
				}
			},
			"response": []
		},
		{
			"name": "Удаление комментария администратором",
			"event": [
				{
					"listen": "prerequest",
					"script": {
						"exec": [
							"const main = async () => {\r",
							"    const api = new API(pm);\r",
							"    const rnd = new RandomUtils();\r",
							"\r",
							"    try {\r",
							"        const user = await api.addUser(rnd.getUser());\r",
							"        const category = await api.addCategory(rnd.getCategory());\r",
							"        let eventBody = rnd.getEvent(category.id);\r",
							"        eventBody['requestModeration'] = true\r",
							"        let event = await api.addEvent(user.id, eventBody);\r",
							"        event = await api.publishEvent(event.id);\r",
							"        const comment = await api.addComment(user.id, event.id, rnd.getComment());\r",
							"\r",
							"        pm.collectionVariables.set(\"uid\", user.id);\r",
							"        pm.collectionVariables.set(\"commentId\", comment.id);\r",
							"        \r",
							"    } catch(err) {\r",
							"        console.error(\"Ошибка при подготовке тестовых данных.\", err);\r",
							"    }\r",
							"};\r",
							"\r",
							"const interval = setInterval(() => {}, 1000);\r",
							"\r",
							"setTimeout(async () => \r",
							"    {\r",
							"        try {\r",
							"            // выполняем наш скрипт\r",
							"            await main();\r",
							"        } catch (e) {\r",
							"            console.error(e);\r",
							"        } finally {\r",
							"            clearInterval(interval);\r",
							"        }\r",
							"    },  \r",
							"    100 \r",
							");"
						],
						"type": "text/javascript",
						"packages": {}
					}
				},
				{
					"listen": "test",
					"script": {
						"exec": [
							"pm.test(\"Ответ должен содержать код статуса 204\", function () {\r",
							"    pm.response.to.have.status(204);\r",
							"});"
						],
						"type": "text/javascript",
						"packages": {}
					}
				}
			],
			"request": {
				"method": "DELETE",
				"header": [],
				"url": {
					"raw": "{{baseUrl}}/admin/comments/:commentId",
					"host": [
						"{{baseUrl}}"
					],
					"path": [
						"admin",
						"comments",
						":commentId"
					],
					"variable": [
						{
							"key": "commentId",
							"value": "{{commentId}}",
							"description": "id комментария"
						}
					]
				}
			},
			"response": []
		},
		{
			"name": "Публичный запрос всех комментариев к событию",
			"event": [
				{
					"listen": "prerequest",
					"script": {
						"exec": [
							"const main = async () => {\r",
							"    const api = new API(pm);\r",
							"    const rnd = new RandomUtils();\r",
							"\r",
							"    try {\r",
							"        const user1 = await api.addUser(rnd.getUser());\r",
							"        const user2 = await api.addUser(rnd.getUser());\r",
							"\r",
							"        const category = await api.addCategory(rnd.getCategory());\r",
							"        let eventBody = rnd.getEvent(category.id);\r",
							"        eventBody['requestModeration'] = true\r",
							"        let event = await api.addEvent(user1.id, eventBody);\r",
							"        event = await api.publishEvent(event.id);\r",
							"        const comment1 = await api.addComment(user1.id, event.id, rnd.getComment());\r",
							"        const comment2 = await api.addComment(user2.id, event.id, rnd.getComment());\r",
							"\r",
							"        pm.collectionVariables.set(\"uid\", user1.id);\r",
							"        pm.collectionVariables.set(\"eid\", event.id);\r",
							"        pm.collectionVariables.set(\"response\", [{comment1}, {comment2}]);\r",
							"\r",
							"    } catch(err) {\r",
							"        console.error(\"Ошибка при подготовке тестовых данных.\", err);\r",
							"    }\r",
							"};\r",
							"\r",
							"const interval = setInterval(() => {}, 1000);\r",
							"\r",
							"setTimeout(async () => \r",
							"    {\r",
							"        try {\r",
							"            // выполняем наш скрипт\r",
							"            await main();\r",
							"        } catch (e) {\r",
							"            console.error(e);\r",
							"        } finally {\r",
							"            clearInterval(interval);\r",
							"        }\r",
							"    },  \r",
							"    100 \r",
							");"
						],
						"type": "text/javascript",
						"packages": {}
					}
				},
				{
					"listen": "test",
					"script": {
						"exec": [
							"pm.test(\"Ответ должен содержать код статуса 200\", function () {\r",
							"    pm.response.to.be.ok;\r",
							"});\r",
							"pm.test(\"Ответ должен содержать список комментариев\", function () {\r",
							"    pm.response.to.be.withBody;\r",
							"    pm.response.to.be.json;\r",
							"    var jsonData = pm.response.json();\r",
							"    pm.expect(jsonData.length, 'длина списка должна быть равна 2').to.eql(2);\r",
							"});"
						],
						"type": "text/javascript",
						"packages": {}
					}
				}
			],
			"request": {
				"method": "GET",
				"header": [],
				"url": {
					"raw": "{{baseUrl}}/events/:eventId/comments",
					"host": [
						"{{baseUrl}}"
					],
					"path": [
						"events",
						":eventId",
						"comments"
					],
					"variable": [
						{
							"key": "eventId",
							"value": "{{eid}}",
							"description": "id текущего события "
						}
					]
				}
			},
			"response": []
		},
		{
			"name": "Публичный запрос всех комментариев (событие не существует или не опубликовано)",
			"event": [
				{
					"listen": "prerequest",
					"script": {
						"exec": [
							"const main = async () => {\r",
							"    const api = new API(pm);\r",
							"    const rnd = new RandomUtils();\r",
							"\r",
							"    try {\r",
							"        const user1 = await api.addUser(rnd.getUser());\r",
							"        const user2 = await api.addUser(rnd.getUser());\r",
							"\r",
							"        const category = await api.addCategory(rnd.getCategory());\r",
							"        let eventBody = rnd.getEvent(category.id);\r",
							"        eventBody['requestModeration'] = true\r",
							"        let event = await api.addEvent(user1.id, eventBody);\r",
							"        event = await api.publishEvent(event.id);\r",
							"        const comment1 = await api.addComment(user1.id, event.id, rnd.getComment());\r",
							"        const comment2 = await api.addComment(user2.id, event.id, rnd.getComment());\r",
							"\r",
							"        pm.collectionVariables.set(\"uid\", user1.id);\r",
							"        pm.collectionVariables.set(\"eid\", event.id);\r",
							"        pm.collectionVariables.set(\"response\", [{comment1}, {comment2}]);\r",
							"\r",
							"    } catch(err) {\r",
							"        console.error(\"Ошибка при подготовке тестовых данных.\", err);\r",
							"    }\r",
							"};\r",
							"\r",
							"const interval = setInterval(() => {}, 1000);\r",
							"\r",
							"setTimeout(async () => \r",
							"    {\r",
							"        try {\r",
							"            // выполняем наш скрипт\r",
							"            await main();\r",
							"        } catch (e) {\r",
							"            console.error(e);\r",
							"        } finally {\r",
							"            clearInterval(interval);\r",
							"        }\r",
							"    },  \r",
							"    100 \r",
							");"
						],
						"type": "text/javascript",
						"packages": {}
					}
				},
				{
					"listen": "test",
					"script": {
						"exec": [
							"pm.test(\"Статус ответа 404. Событие не найдено.\", function () {\r",
							"    pm.expect(pm.response.code).to.be.oneOf([404]);\r",
							"});"
						],
						"type": "text/javascript",
						"packages": {}
					}
				}
			],
			"request": {
				"method": "GET",
				"header": [],
				"url": {
					"raw": "{{baseUrl}}/events/:eventId/comments",
					"host": [
						"{{baseUrl}}"
					],
					"path": [
						"events",
						":eventId",
						"comments"
					],
					"variable": [
						{
							"key": "eventId",
							"value": "9999",
							"description": "id события"
						}
					]
				}
			},
			"response": []
		}
	],
	"event": [
		{
			"listen": "prerequest",
			"script": {
				"type": "text/javascript",
				"packages": {},
				"exec": [
					"API = class {\r",
					"    constructor(postman, verbose = false, baseUrl = \"http://localhost:8080\") {\r",
					"        this.baseUrl = baseUrl;\r",
					"        this.pm = postman;\r",
					"        this._verbose = verbose;\r",
					"    }\r",
					"\r",
					"// добавление нового комментария (аналогично событиям)\r",
					"    async addComment(userId, eventId, comment, verbose=null) {\r",
					"        return this.post(\"/users/\" + userId + \"/events/\" + eventId + \"/comments\", comment, \"Ошибка при добавлении нового события: \", verbose);\r",
					"    }\r",
					"\r",
					"    async addUser(user, verbose=null) {\r",
					"        return this.post(\"/admin/users\", user, \"Ошибка при добавлении нового пользователя: \", verbose);\r",
					"    }\r",
					"\r",
					"    async addCategory(category, verbose=null) {\r",
					"        return this.post(\"/admin/categories\", category, \"Ошибка при добавлении новой категории: \", verbose);\r",
					"    }\r",
					"\r",
					"    async addEvent(userId, event, verbose=null) {\r",
					"        return this.post(\"/users/\" + userId + \"/events\", event, \"Ошибка при добавлении нового события: \", verbose);\r",
					"    }\r",
					"\r",
					"    async addCompilation(compilation, verbose=null) {\r",
					"        return this.post(\"/admin/compilations\", compilation, \"Ошибка при добавлении новой подборки: \", verbose);\r",
					"    }\r",
					"\r",
					"    async publishParticipationRequest(eventId, userId, verbose=null) {\r",
					"        return this.post('/users/' + userId + '/requests?eventId=' + eventId, null, \"Ошибка при добавлении нового запроса на участие в событии\", verbose);\r",
					"    }\r",
					"\r",
					"    async publishEvent(eventId, verbose=null) {\r",
					"        return this.patch('/admin/events/' + eventId, {stateAction: \"PUBLISH_EVENT\"}, \"Ошибка при публикации события\", verbose);\r",
					"    }\r",
					"    \r",
					"    async rejectEvent(eventId, verbose=null) {\r",
					"        return this.patch('/admin/events/' + eventId, {stateAction: \"REJECT_EVENT\"}, \"Ошибка при отмене события\", verbose);\r",
					"    }\r",
					"\r",
					"    async acceptParticipationRequest(eventId, userId, reqId, verbose=null) {\r",
					"        return this.patch('/users/' + userId + '/events/' + eventId + '/requests/', {requestIds:[reqId], status: \"CONFIRMED\"}, \"Ошибка при принятии заявки на участие в событии\", verbose);\r",
					"    }\r",
					"\r",
					"    async findCategory(catId, verbose=null) {\r",
					"        return this.get('/categories/' + catId, null, \"Ошибка при поиске категории по id\", verbose);\r",
					"    }\r",
					"\r",
					"    async findCompilation(compId, verbose=null) {\r",
					"        return this.get('/compilations/' + compId, null, \"Ошибка при поиске подборки по id\", verbose);\r",
					"    }\r",
					"\r",
					"    async findEvent(eventId, verbose=null) {\r",
					"        return this.get('/events/' + eventId, null, \"Ошибка при поиске события по id\", verbose);\r",
					"    }\r",
					"\r",
					"    async findUser(userId, verbose=null) {\r",
					"        return this.get('/admin/users?ids=' + userId, null, \"Ошибка при поиске пользователя по id\", verbose);\r",
					"    }\r",
					"\r",
					"    async post(path, body, errorText = \"Ошибка при выполнении post-запроса: \", verbose=null) {\r",
					"        return this.sendRequest(\"POST\", path, body, errorText, verbose);\r",
					"    }\r",
					"\r",
					"    async patch(path, body = null, errorText = \"Ошибка при выполнении patch-запроса: \", verbose=null) {\r",
					"        return this.sendRequest(\"PATCH\", path, body, errorText, verbose);\r",
					"    }\r",
					"\r",
					"    async get(path, body = null, errorText = \"Ошибка при выполнении get-запроса: \", verbose=null) {\r",
					"        return this.sendRequest(\"GET\", path, body, errorText, verbose);\r",
					"    }\r",
					"    async sendRequest(method, path, body=null, errorText = \"Ошибка при выполнении запроса: \", verbose=null) {\r",
					"        return new Promise((resolve, reject) => {\r",
					"            verbose = verbose == null ? this._verbose : verbose;\r",
					"            const request = {\r",
					"                url: this.baseUrl + path,\r",
					"                method: method,\r",
					"                body: body == null ? \"\" : JSON.stringify(body),\r",
					"                header: { \"Content-Type\": \"application/json\" },\r",
					"            };\r",
					"            if(verbose) {\r",
					"                console.log(\"Отправляю запрос: \", request);\r",
					"            }\r",
					"\r",
					"            try {\r",
					"                this.pm.sendRequest(request, (error, response) => {\r",
					"                    if(error || (response.code >= 400 && response.code <= 599)) {\r",
					"                        let err = error ? error : JSON.stringify(response.json());\r",
					"                        console.error(\"При выполнении запроса к серверу возникла ошика.\\n\", err,\r",
					"                             \"\\nДля отладки проблемы повторите такой же запрос к вашей программе \" + \r",
					"                             \"на локальном компьютере. Данные запроса:\\n\", JSON.stringify(request));\r",
					"\r",
					"                        reject(new Error(errorText + err));\r",
					"                    }\r",
					"                    if(verbose) {\r",
					"                        console.log(\"Результат обработки запроса: код состояния - \", response.code, \", тело: \", response.json());\r",
					"                    }\r",
					"                    if (response.stream.length === 0){\r",
					"                        reject(new Error('Отправлено пустое тело ответа'))\r",
					"                    }else{\r",
					"                        resolve(response.json());\r",
					"                    }\r",
					"                });\r",
					"                \r",
					"            } catch(err) {\r",
					"                if(verbose) {\r",
					"                    console.error(errorText, err);\r",
					"                }\r",
					"                return Promise.reject(err);\r",
					"            }\r",
					"        });\r",
					"    }\r",
					"};\r",
					"\r",
					"RandomUtils = class {\r",
					"    constructor() {}\r",
					"\r",
					"// получение комментария (аналогично категории)\r",
					"    getComment() {\r",
					"        return {\r",
					"            text: pm.variables.replaceIn('{{$randomWord}}') + Math.floor(Math.random() * 100).toString()\r",
					"        };\r",
					"    }\r",
					"\r",
					"\r",
					"    getUser() {\r",
					"        return {\r",
					"            name: pm.variables.replaceIn('{{$randomFullName}}'),\r",
					"            email: pm.variables.replaceIn('{{$randomEmail}}')\r",
					"        };\r",
					"    }\r",
					"\r",
					"    getCategory() {\r",
					"        return {\r",
					"            name: pm.variables.replaceIn('{{$randomWord}}') + Math.floor(Math.random() * 10000 * Math.random()).toString()\r",
					"        };\r",
					"    }\r",
					"\r",
					"    getEvent(categoryId) {\r",
					"        return {\r",
					"            annotation: pm.variables.replaceIn('{{$randomLoremParagraph}}'),\r",
					"            category: categoryId,\r",
					"            description: pm.variables.replaceIn('{{$randomLoremParagraphs}}'),\r",
					"            eventDate: this.getFutureDateTime(),\r",
					"            location: {\r",
					"                lat: parseFloat(pm.variables.replaceIn('{{$randomLatitude}}')),\r",
					"                lon: parseFloat(pm.variables.replaceIn('{{$randomLongitude}}')),\r",
					"            },\r",
					"            paid: pm.variables.replaceIn('{{$randomBoolean}}'),\r",
					"            participantLimit: pm.variables.replaceIn('{{$randomInt}}'),\r",
					"            requestModeration: pm.variables.replaceIn('{{$randomBoolean}}'),\r",
					"            title: pm.variables.replaceIn('{{$randomLoremSentence}}'),\r",
					"        }\r",
					"    }\r",
					"\r",
					"    getCompilation(...eventIds) {\r",
					"        return {\r",
					"            title: pm.variables.replaceIn('{{$randomLoremSentence}}').slice(0, 50),\r",
					"            pinned: pm.variables.replaceIn('{{$randomBoolean}}'),\r",
					"            events: eventIds\r",
					"        };\r",
					"    }\r",
					"\r",
					"\r",
					"    getFutureDateTime(hourShift = 5, minuteShift=0, yearShift=0) {\r",
					"        let moment = require('moment');\r",
					"\r",
					"        let m = moment();\r",
					"        m.add(hourShift, 'hour');\r",
					"        m.add(minuteShift, 'minute');\r",
					"        m.add(yearShift, 'year');\r",
					"\r",
					"        return m.format('YYYY-MM-DD HH:mm:ss');\r",
					"    }\r",
					"\r",
					"    getWord(length = 1) {\r",
					"        let result = '';\r",
					"        const characters = 'ABCDEFGHIJKLMNOPQRSTUVWXYZabcdefghijklmnopqrstuvwxyz0123456789';\r",
					"        const charactersLength = characters.length;\r",
					"        let counter = 0;\r",
					"        while (counter < length) {\r",
					"            result += characters.charAt(Math.floor(Math.random() * charactersLength));\r",
					"            counter += 1;\r",
					"        }\r",
					"        return result;\r",
					"    }\r",
					"}"
				]
			}
		},
		{
			"listen": "test",
			"script": {
				"type": "text/javascript",
				"packages": {},
				"exec": [
					""
				]
			}
		}
	],
	"variable": [
		{
			"key": "baseUrl",
			"value": "http://localhost:8080",
			"type": "string"
		},
		{
			"key": "name",
			"value": "",
			"type": "string"
		},
		{
			"key": "userCount",
			"value": "1",
			"type": "string"
		},
		{
			"key": "catid",
			"value": "1",
			"type": "string"
		},
		{
			"key": "request_body",
			"value": "",
			"type": "string"
		},
		{
			"key": "mail",
			"value": "",
			"type": "string"
		},
		{
			"key": "response",
			"value": "",
			"type": "string"
		},
		{
			"key": "uid",
			"value": "1",
			"type": "string"
		},
		{
			"key": "catname",
			"value": "",
			"type": "string"
		},
		{
			"key": "eid",
			"value": "1",
			"type": "string"
		},
		{
			"key": "compid",
			"value": "1",
			"type": "string"
		},
		{
			"key": "toCheck",
			"value": "",
			"type": "string"
		},
		{
			"key": "newDataToSet",
			"value": "",
			"type": "string"
		},
		{
			"key": "uid1",
			"value": "",
			"type": "string"
		},
		{
			"key": "reqid",
			"value": "1",
			"type": "string"
		},
		{
			"key": "catId",
			"value": "",
			"type": "string"
		},
		{
			"key": "confirmedRequests",
			"value": "",
			"type": "string"
		},
		{
			"key": "responseArr",
			"value": "",
			"type": "string"
		},
		{
			"key": "source1",
			"value": "",
			"type": "string"
		},
		{
			"key": "source2",
			"value": "",
			"type": "string"
		},
		{
			"key": "fromId",
			"value": "0",
			"type": "string"
		},
		{
			"key": "source",
			"value": "",
			"type": "string"
		},
		{
			"key": "commentId",
			"value": "",
			"type": "string"
		}
	]
}